{
    "name": "Cohort",
    "fields": [
        {
            "fieldName": "startDate",
            "fieldType": "LocalDate",
            "fieldValidateRules": [
                "required"
            ]
        }
    ],
    "relationships": [
        {
            "relationshipType": "many-to-one",
            "relationshipName": "teacher",
            "otherEntityName": "teacher",
            "otherEntityField": "id"
        },
        {
            "relationshipType": "many-to-one",
            "relationshipName": "student",
            "otherEntityName": "student",
            "otherEntityField": "id"
        }
    ],
    "changelogDate": "20180925145727",
    "entityTableName": "cohort",
    "dto": "no",
    "pagination": "no",
    "service": "no",
    "jpaMetamodelFiltering": false,
    "fluentMethods": true,
    "clientRootFolder": "",
    "applications": "*"
}